WellLogging/__init__.py
WellLogging/NMR/__init__.py
WellLogging/acoustics/__init__.py
WellLogging/atomic/__init__.py
WellLogging/electric/Archie.py
WellLogging/electric/Doll.py
WellLogging/electric/__init__.py
WellLogging/interpretation/K.py
WellLogging/interpretation/PEG.py
WellLogging/interpretation/Sw.py
WellLogging/interpretation/Vsh.py
WellLogging/interpretation/__init__.py
WellLogging/radioactivity/__init__.py
WellLogging/sound/__init__.py
WellLogging-0.1.7.dist-info/METADATA
WellLogging-0.1.7.dist-info/WHEEL
WellLogging-0.1.7.dist-info/top_level.txt
WellLogging-0.1.7.dist-info/RECORD
