Metadata-Version: 2.1
Name: WellLogging
Version: 0.1.7
Summary: 测井中常用的数学公式
Home-page: https://github.com/czy-123/WL.git
Author: 程智勇
Author-email: 807291574@qq.com
License: MIT
Platform: UNKNOWN
Classifier: License :: OSI Approved :: MIT License
Classifier: Programming Language :: Python
Classifier: Programming Language :: Python :: 3
Classifier: Programming Language :: Python :: 3.6
Classifier: Programming Language :: Python :: Implementation :: CPython
Classifier: Programming Language :: Python :: Implementation :: PyPy
Requires-Python: >=3.5.0
Requires-Dist: numpy
